ramanbiolibui/__init__.py
ramanbiolibui/__main__.py
ramanbiolibui/app.py
ramanbiolibui/handlers/__init__.py
ramanbiolibui/handlers/jshandler.py
ramanbiolibui/handlers/linkhandler.py
ramanbiolibui/hooks/hook-cefpython3.py
ramanbiolibui/img/icfo.png
ramanbiolibui/img/logo.png
ramanbiolibui/img/uoc.png
ramanbiolibui/static/jquery.min.js.js
ramanbiolibui/static/scripts.js
ramanbiolibui/static/styles.css
ramanbiolibui/templates/index.html
ramanbiolibui/templates/results.html
ramanbiolibui/templates/search.html
ramanbiolibui/utils/__init__.py
ramanbiolibui/utils/files.py
ramanbiolibui/utils/search.py
ramanbiolib_ui-1.0.0rc5.dist-info/LICENSE.txt
ramanbiolib_ui-1.0.0rc5.dist-info/METADATA
ramanbiolib_ui-1.0.0rc5.dist-info/WHEEL
ramanbiolib_ui-1.0.0rc5.dist-info/entry_points.txt
ramanbiolib_ui-1.0.0rc5.dist-info/top_level.txt
ramanbiolib_ui-1.0.0rc5.dist-info/RECORD
