Metadata-Version: 2.1
Name: ramanbiolib-ui
Version: 1.0.0rc5
Summary: UI for ramanbiolib. Biomolecules identification search using Raman spectra.
Author: Marcelo Teran Miranda
License: GNU GPLv3
Project-URL: Homepage, https://github.com/mteranm/ramanbiolib-ui
Project-URL: Repository, https://github.com/mteranm/ramanbiolib-ui
Keywords: raman,spectroscopy,biomolecules
Classifier: License :: OSI Approved :: GNU General Public License v3 (GPLv3)
Classifier: Programming Language :: Python :: 3
Requires-Python: <3.8,>=3.7
License-File: LICENSE.txt
Requires-Dist: cefpython3 ==66.0
Requires-Dist: numpy <1.22.0,>=1.21.6
Requires-Dist: pandas <2.0,>=1.1.5
Requires-Dist: scipy <1.8,>=1.7.3
Requires-Dist: plotly <6.0,>=5.0
Requires-Dist: ramanbiolib
